DjangoCrud/__init__.py
DjangoCrud/admin.py
DjangoCrud/apps.py
DjangoCrud/models.py
DjangoCrud/tests.py
DjangoCrud/views.py
DjangoCrud/migrations/0001_initial.py
DjangoCrud/migrations/__init__.py
my_django_crud-1.1.dist-info/LICENSE
my_django_crud-1.1.dist-info/METADATA
my_django_crud-1.1.dist-info/WHEEL
my_django_crud-1.1.dist-info/top_level.txt
my_django_crud-1.1.dist-info/RECORD
